release_mgr/__init__.py
release_mgr/cli.py
release_mgr/git.py
release_mgr/github.py
release_mgr/release.py
release_mgr/version.py
release_mgr/version_files/__init__.py
release_mgr/version_files/cargo_toml.py
release_mgr/version_files/dunder_version.py
release_mgr/version_files/lerna_json.py
release_mgr/version_files/package_json.py
release_mgr/version_files/pyproject.py
release_mgr/version_files/setup_py.py
release_mgr/version_files/version_file.py
tests/__init__.py
tests/test_cargo_toml.py
tests/test_version.py
release_mgr-0.3.1.dist-info/METADATA
release_mgr-0.3.1.dist-info/WHEEL
release_mgr-0.3.1.dist-info/entry_points.txt
release_mgr-0.3.1.dist-info/top_level.txt
release_mgr-0.3.1.dist-info/RECORD
