Metadata-Version: 2.1
Name: release-mgr
Version: 0.3.1
Summary: A simple tool for managing software releases on GitHub.
Home-page: https://github.com/chasinglogic/gh-release
Author: Mathew Robinson
Author-email: chasinglogic@gmail.com
License: GPL-3.0
Platform: any
Classifier: Development Status :: 4 - Beta
Classifier: Environment :: Console
Classifier: Intended Audience :: Developers
Classifier: License :: OSI Approved :: GNU Affero General Public License v3
Classifier: Operating System :: POSIX
Classifier: Operating System :: MacOS
Classifier: Operating System :: Microsoft :: Windows
Classifier: Programming Language :: Python
Classifier: Programming Language :: Python :: 3
Classifier: Topic :: Software Development :: Libraries :: Python Modules
Requires-Dist: requests (==2.25.1)
